guis.py
guis-0.0.6.dist-info/LICENSE.txt
guis-0.0.6.dist-info/METADATA
guis-0.0.6.dist-info/WHEEL
guis-0.0.6.dist-info/top_level.txt
guis-0.0.6.dist-info/RECORD
