Metadata-Version: 2.1
Name: guis
Version: 0.0.6
Summary: This module is called GUIS which means GUI Simplified / Graphial User Interface Simplified.
Home-page: https://github.com/Coding-bros/GUIS
Author: Karthik
Author-email: bkp.karthi@gmail.com
License: UNKNOWN
Platform: UNKNOWN
Classifier: Programming Language :: Python :: 3
Classifier: Programming Language :: Python :: 3.6
Classifier: Programming Language :: Python :: 3.7
Classifier: Programming Language :: Python :: 3.8
Classifier: Programming Language :: Python :: 3.9
Classifier: Operating System :: OS Independent
